test/__init__.py
test/test_ultimaker.py
ultimaker/__init__.py
ultimaker/api.py
ultimaker_printer_api-0.0.6.dist-info/LICENSE
ultimaker_printer_api-0.0.6.dist-info/METADATA
ultimaker_printer_api-0.0.6.dist-info/WHEEL
ultimaker_printer_api-0.0.6.dist-info/top_level.txt
ultimaker_printer_api-0.0.6.dist-info/RECORD
