Metadata-Version: 2.1
Name: ultimaker-printer-api
Version: 0.0.6
Summary: An Ultimaker Printer API client implementation in Python
Home-page: https://github.com/vanderbilt-design-studio/python-ultimaker-printer-api
Author: Sameer Puri
Author-email: purisame@spuri.io
License: UNKNOWN
Platform: UNKNOWN
Classifier: Programming Language :: Python :: 3
Classifier: License :: OSI Approved :: MIT License
Classifier: Operating System :: OS Independent
Requires-Dist: zeroconf
Requires-Dist: requests
Requires-Dist: uuid
Requires-Dist: pillow
Requires-Dist: imagehash
